{
  "updatedAt": "2026-06-29T10:13:00+09:00",
  "source": "Google Trends RSS JP",
  "note": "Google Trends RSSと公開RSS検索から候補フレーズを抽出し、ウォッチリストと除外語でSNS投稿向けテーマに絞り込んでいます。",
  "items": [
    {
      "id": "4304296be742",
      "keyword": "fivbバレーボール・ネイションズリーグ 男子",
      "watchlist": "actual_public_trend",
      "watchlistLabel": "実トレンド",
      "rank": 2,
      "previousRank": null,
      "rankChange": null,
      "score": 100,
      "previousScore": null,
      "scoreChange": 100,
      "yesterdayScore": null,
      "yesterdayChange": null,
      "direction": "new",
      "trendStatus": "actual_trend",
      "appearCount": 1,
      "signalType": "daily_trend",
      "evidenceCount": null,
      "previousEvidenceCount": null,
      "evidenceChange": null,
      "capturedAt": "2026-06-29T10:13:00+09:00",
      "series": [
        {
          "time": "10:13",
          "score": 100
        }
      ],
      "observeUrl": "https://trends.google.com/trending/rss?geo=JP"
    },
    {
      "id": "5f3cc2602d89",
      "keyword": "ハイドラガンダム",
      "watchlist": "actual_public_trend",
      "watchlistLabel": "実トレンド",
      "rank": 4,
      "previousRank": null,
      "rankChange": null,
      "score": 97,
      "previousScore": null,
      "scoreChange": 97,
      "yesterdayScore": null,
      "yesterdayChange": null,
      "direction": "new",
      "trendStatus": "actual_trend",
      "appearCount": 1,
      "signalType": "daily_trend",
      "evidenceCount": null,
      "previousEvidenceCount": null,
      "evidenceChange": null,
      "capturedAt": "2026-06-29T10:13:00+09:00",
      "series": [
        {
          "time": "10:13",
          "score": 97
        }
      ],
      "observeUrl": "https://trends.google.com/trending/rss?geo=JP"
    },
    {
      "id": "ea0aca72bbdb",
      "keyword": "アスレチックス",
      "watchlist": "actual_public_trend",
      "watchlistLabel": "実トレンド",
      "rank": 5,
      "previousRank": null,
      "rankChange": null,
      "score": 95,
      "previousScore": null,
      "scoreChange": 95,
      "yesterdayScore": null,
      "yesterdayChange": null,
      "direction": "new",
      "trendStatus": "actual_trend",
      "appearCount": 1,
      "signalType": "daily_trend",
      "evidenceCount": null,
      "previousEvidenceCount": null,
      "evidenceChange": null,
      "capturedAt": "2026-06-29T10:13:00+09:00",
      "series": [
        {
          "time": "10:13",
          "score": 95
        }
      ],
      "observeUrl": "https://trends.google.com/trending/rss?geo=JP"
    },
    {
      "id": "e8b8483aeee7",
      "keyword": "ミス・コンテスト",
      "watchlist": "actual_public_trend",
      "watchlistLabel": "実トレンド",
      "rank": 7,
      "previousRank": null,
      "rankChange": null,
      "score": 91,
      "previousScore": null,
      "scoreChange": 91,
      "yesterdayScore": null,
      "yesterdayChange": null,
      "direction": "new",
      "trendStatus": "actual_trend",
      "appearCount": 1,
      "signalType": "daily_trend",
      "evidenceCount": null,
      "previousEvidenceCount": null,
      "evidenceChange": null,
      "capturedAt": "2026-06-29T10:13:00+09:00",
      "series": [
        {
          "time": "10:13",
          "score": 91
        }
      ],
      "observeUrl": "https://trends.google.com/trending/rss?geo=JP"
    },
    {
      "id": "85ed050f1ffe",
      "keyword": "ボウリング企画",
      "watchlist": "local_leisure",
      "watchlistLabel": "地域・レジャー",
      "rank": 26,
      "previousRank": 26,
      "rankChange": 0,
      "score": 88,
      "previousScore": 58,
      "scoreChange": 30,
      "yesterdayScore": null,
      "yesterdayChange": null,
      "direction": "up",
      "trendStatus": "rising",
      "appearCount": 14,
      "signalType": "configured_rss",
      "evidenceCount": 11,
      "previousEvidenceCount": 8,
      "evidenceChange": 3,
      "capturedAt": "2026-06-29T10:13:00+09:00",
      "series": [
        {
          "time": "10:03",
          "score": 56
        },
        {
          "time": "10:04",
          "score": 56
        },
        {
          "time": "10:06",
          "score": 56
        },
        {
          "time": "10:06",
          "score": 68
        },
        {
          "time": "10:08",
          "score": 58
        },
        {
          "time": "10:13",
          "score": 88
        }
      ],
      "observeUrl": "https://news.google.com/search?q=%E3%83%9C%E3%82%A6%E3%83%AA%E3%83%B3%E3%82%B0%20SNS%20%E4%BC%81%E7%94%BB&hl=ja&gl=JP&ceid=JP%3Aja"
    },
    {
      "id": "8e688453651f",
      "keyword": "池田朱那",
      "watchlist": "actual_public_trend",
      "watchlistLabel": "実トレンド",
      "rank": 9,
      "previousRank": null,
      "rankChange": null,
      "score": 87,
      "previousScore": null,
      "scoreChange": 87,
      "yesterdayScore": null,
      "yesterdayChange": null,
      "direction": "new",
      "trendStatus": "actual_trend",
      "appearCount": 1,
      "signalType": "daily_trend",
      "evidenceCount": null,
      "previousEvidenceCount": null,
      "evidenceChange": null,
      "capturedAt": "2026-06-29T10:13:00+09:00",
      "series": [
        {
          "time": "10:13",
          "score": 87
        }
      ],
      "observeUrl": "https://trends.google.com/trending/rss?geo=JP"
    },
    {
      "id": "c7c828a4ad63",
      "keyword": "おじさん構文",
      "watchlist": "sns_platform",
      "watchlistLabel": "SNSトレンド",
      "rank": 3,
      "previousRank": 3,
      "rankChange": 0,
      "score": 65,
      "previousScore": 65,
      "scoreChange": 0,
      "yesterdayScore": null,
      "yesterdayChange": null,
      "direction": "flat",
      "trendStatus": "flat",
      "appearCount": 11,
      "signalType": "discovered_phrase",
      "evidenceCount": 7,
      "previousEvidenceCount": 7,
      "evidenceChange": 0,
      "capturedAt": "2026-06-29T10:13:00+09:00",
      "series": [
        {
          "time": "10:03",
          "score": 65
        },
        {
          "time": "10:04",
          "score": 65
        },
        {
          "time": "10:06",
          "score": 59
        },
        {
          "time": "10:06",
          "score": 65
        },
        {
          "time": "10:08",
          "score": 65
        },
        {
          "time": "10:13",
          "score": 65
        }
      ],
      "observeUrl": "https://news.google.com/search?q=%E3%81%8A%E3%81%98%E3%81%95%E3%82%93%E6%A7%8B%E6%96%87&hl=ja&gl=JP&ceid=JP%3Aja"
    },
    {
      "id": "ff5b67a75b2c",
      "keyword": "ダンスチャレンジ",
      "watchlist": "sns_platform",
      "watchlistLabel": "SNSトレンド",
      "rank": 12,
      "previousRank": 12,
      "rankChange": 0,
      "score": 65,
      "previousScore": 65,
      "scoreChange": 0,
      "yesterdayScore": null,
      "yesterdayChange": null,
      "direction": "flat",
      "trendStatus": "flat",
      "appearCount": 11,
      "signalType": "discovered_phrase",
      "evidenceCount": 4,
      "previousEvidenceCount": 4,
      "evidenceChange": 0,
      "capturedAt": "2026-06-29T10:13:00+09:00",
      "series": [
        {
          "time": "10:03",
          "score": 65
        },
        {
          "time": "10:04",
          "score": 65
        },
        {
          "time": "10:06",
          "score": 65
        },
        {
          "time": "10:06",
          "score": 65
        },
        {
          "time": "10:08",
          "score": 65
        },
        {
          "time": "10:13",
          "score": 65
        }
      ],
      "observeUrl": "https://news.google.com/search?q=%E3%83%80%E3%83%B3%E3%82%B9%E3%83%81%E3%83%A3%E3%83%AC%E3%83%B3%E3%82%B8&hl=ja&gl=JP&ceid=JP%3Aja"
    },
    {
      "id": "e8c7ef119ba0",
      "keyword": "学校あるある",
      "watchlist": "sns_platform",
      "watchlistLabel": "SNSトレンド",
      "rank": 12,
      "previousRank": 12,
      "rankChange": 0,
      "score": 65,
      "previousScore": 65,
      "scoreChange": 0,
      "yesterdayScore": null,
      "yesterdayChange": null,
      "direction": "flat",
      "trendStatus": "flat",
      "appearCount": 11,
      "signalType": "discovered_phrase",
      "evidenceCount": 4,
      "previousEvidenceCount": 4,
      "evidenceChange": 0,
      "capturedAt": "2026-06-29T10:13:00+09:00",
      "series": [
        {
          "time": "10:03",
          "score": 65
        },
        {
          "time": "10:04",
          "score": 65
        },
        {
          "time": "10:06",
          "score": 32
        },
        {
          "time": "10:06",
          "score": 65
        },
        {
          "time": "10:08",
          "score": 65
        },
        {
          "time": "10:13",
          "score": 65
        }
      ],
      "observeUrl": "https://news.google.com/search?q=%E5%AD%A6%E6%A0%A1%E3%81%82%E3%82%8B%E3%81%82%E3%82%8B&hl=ja&gl=JP&ceid=JP%3Aja"
    },
    {
      "id": "dd3c832f44b6",
      "keyword": "沖縄飲み会あるある",
      "watchlist": "sns_platform",
      "watchlistLabel": "SNSトレンド",
      "rank": 15,
      "previousRank": 15,
      "rankChange": 0,
      "score": 63,
      "previousScore": 65,
      "scoreChange": -2,
      "yesterdayScore": null,
      "yesterdayChange": null,
      "direction": "flat",
      "trendStatus": "flat",
      "appearCount": 11,
      "signalType": "discovered_phrase",
      "evidenceCount": 3,
      "previousEvidenceCount": 3,
      "evidenceChange": 0,
      "capturedAt": "2026-06-29T10:13:00+09:00",
      "series": [
        {
          "time": "10:03",
          "score": 65
        },
        {
          "time": "10:04",
          "score": 65
        },
        {
          "time": "10:06",
          "score": 49
        },
        {
          "time": "10:06",
          "score": 65
        },
        {
          "time": "10:08",
          "score": 65
        },
        {
          "time": "10:13",
          "score": 63
        }
      ],
      "observeUrl": "https://news.google.com/search?q=%E6%B2%96%E7%B8%84%E9%A3%B2%E3%81%BF%E4%BC%9A%E3%81%82%E3%82%8B%E3%81%82%E3%82%8B&hl=ja&gl=JP&ceid=JP%3Aja"
    },
    {
      "id": "6a648247e136",
      "keyword": "TikTokチャレンジ",
      "watchlist": "sns_platform",
      "watchlistLabel": "SNSトレンド",
      "rank": 26,
      "previousRank": 26,
      "rankChange": 0,
      "score": 60,
      "previousScore": 62,
      "scoreChange": -2,
      "yesterdayScore": null,
      "yesterdayChange": null,
      "direction": "flat",
      "trendStatus": "flat",
      "appearCount": 14,
      "signalType": "configured_rss",
      "evidenceCount": 20,
      "previousEvidenceCount": 20,
      "evidenceChange": 0,
      "capturedAt": "2026-06-29T10:13:00+09:00",
      "series": [
        {
          "time": "10:03",
          "score": 62
        },
        {
          "time": "10:04",
          "score": 62
        },
        {
          "time": "10:06",
          "score": 62
        },
        {
          "time": "10:06",
          "score": 62
        },
        {
          "time": "10:08",
          "score": 62
        },
        {
          "time": "10:13",
          "score": 60
        }
      ],
      "observeUrl": "https://news.google.com/search?q=TikTok%20%E3%83%81%E3%83%A3%E3%83%AC%E3%83%B3%E3%82%B8&hl=ja&gl=JP&ceid=JP%3Aja"
    },
    {
      "id": "94bfd629d3aa",
      "keyword": "TikTokトレンド音源",
      "watchlist": "sns_platform",
      "watchlistLabel": "SNSトレンド",
      "rank": 26,
      "previousRank": 26,
      "rankChange": 0,
      "score": 60,
      "previousScore": 62,
      "scoreChange": -2,
      "yesterdayScore": null,
      "yesterdayChange": null,
      "direction": "flat",
      "trendStatus": "flat",
      "appearCount": 14,
      "signalType": "configured_rss",
      "evidenceCount": 20,
      "previousEvidenceCount": 20,
      "evidenceChange": 0,
      "capturedAt": "2026-06-29T10:13:00+09:00",
      "series": [
        {
          "time": "10:03",
          "score": 62
        },
        {
          "time": "10:04",
          "score": 62
        },
        {
          "time": "10:06",
          "score": 62
        },
        {
          "time": "10:06",
          "score": 62
        },
        {
          "time": "10:08",
          "score": 62
        },
        {
          "time": "10:13",
          "score": 60
        }
      ],
      "observeUrl": "https://news.google.com/search?q=TikTok%20%E3%83%88%E3%83%AC%E3%83%B3%E3%83%89%E9%9F%B3%E6%BA%90&hl=ja&gl=JP&ceid=JP%3Aja"
    },
    {
      "id": "c72bd46a9b6b",
      "keyword": "鹿児島グルメ",
      "watchlist": "local_leisure",
      "watchlistLabel": "地域・レジャー",
      "rank": 26,
      "previousRank": 26,
      "rankChange": 0,
      "score": 60,
      "previousScore": 62,
      "scoreChange": -2,
      "yesterdayScore": null,
      "yesterdayChange": null,
      "direction": "flat",
      "trendStatus": "flat",
      "appearCount": 14,
      "signalType": "configured_rss",
      "evidenceCount": 20,
      "previousEvidenceCount": 20,
      "evidenceChange": 0,
      "capturedAt": "2026-06-29T10:13:00+09:00",
      "series": [
        {
          "time": "10:03",
          "score": 62
        },
        {
          "time": "10:04",
          "score": 62
        },
        {
          "time": "10:06",
          "score": 62
        },
        {
          "time": "10:06",
          "score": 62
        },
        {
          "time": "10:08",
          "score": 62
        },
        {
          "time": "10:13",
          "score": 60
        }
      ],
      "observeUrl": "https://news.google.com/search?q=%E9%B9%BF%E5%85%90%E5%B3%B6%20%E3%82%B0%E3%83%AB%E3%83%A1%20%E8%A9%B1%E9%A1%8C&hl=ja&gl=JP&ceid=JP%3Aja"
    },
    {
      "id": "b130739585aa",
      "keyword": "リールあるある",
      "watchlist": "format",
      "watchlistLabel": "投稿フォーマット",
      "rank": 26,
      "previousRank": 26,
      "rankChange": 0,
      "score": 59,
      "previousScore": 61,
      "scoreChange": -2,
      "yesterdayScore": null,
      "yesterdayChange": null,
      "direction": "flat",
      "trendStatus": "flat",
      "appearCount": 14,
      "signalType": "configured_rss",
      "evidenceCount": 20,
      "previousEvidenceCount": 20,
      "evidenceChange": 0,
      "capturedAt": "2026-06-29T10:13:00+09:00",
      "series": [
        {
          "time": "10:03",
          "score": 61
        },
        {
          "time": "10:04",
          "score": 61
        },
        {
          "time": "10:06",
          "score": 61
        },
        {
          "time": "10:06",
          "score": 61
        },
        {
          "time": "10:08",
          "score": 61
        },
        {
          "time": "10:13",
          "score": 59
        }
      ],
      "observeUrl": "https://news.google.com/search?q=Instagram%20%E3%83%AA%E3%83%BC%E3%83%AB%20%E3%81%82%E3%82%8B%E3%81%82%E3%82%8B&hl=ja&gl=JP&ceid=JP%3Aja"
    },
    {
      "id": "edd25d7b4866",
      "keyword": "YouTube Shortsネタ",
      "watchlist": "sns_platform",
      "watchlistLabel": "SNSトレンド",
      "rank": 26,
      "previousRank": 26,
      "rankChange": 0,
      "score": 59,
      "previousScore": 61,
      "scoreChange": -2,
      "yesterdayScore": null,
      "yesterdayChange": null,
      "direction": "flat",
      "trendStatus": "flat",
      "appearCount": 14,
      "signalType": "configured_rss",
      "evidenceCount": 20,
      "previousEvidenceCount": 20,
      "evidenceChange": 0,
      "capturedAt": "2026-06-29T10:13:00+09:00",
      "series": [
        {
          "time": "10:03",
          "score": 61
        },
        {
          "time": "10:04",
          "score": 61
        },
        {
          "time": "10:06",
          "score": 61
        },
        {
          "time": "10:06",
          "score": 61
        },
        {
          "time": "10:08",
          "score": 61
        },
        {
          "time": "10:13",
          "score": 59
        }
      ],
      "observeUrl": "https://news.google.com/search?q=YouTube%20Shorts%20%E8%A9%B1%E9%A1%8C&hl=ja&gl=JP&ceid=JP%3Aja"
    },
    {
      "id": "ba7567f9e0a0",
      "keyword": "踊ってみた",
      "watchlist": "sns_platform",
      "watchlistLabel": "SNSトレンド",
      "rank": 26,
      "previousRank": 26,
      "rankChange": 0,
      "score": 59,
      "previousScore": 61,
      "scoreChange": -2,
      "yesterdayScore": null,
      "yesterdayChange": null,
      "direction": "flat",
      "trendStatus": "flat",
      "appearCount": 15,
      "signalType": "configured_rss",
      "evidenceCount": 20,
      "previousEvidenceCount": 20,
      "evidenceChange": 0,
      "capturedAt": "2026-06-29T10:13:00+09:00",
      "series": [
        {
          "time": "10:03",
          "score": 61
        },
        {
          "time": "10:04",
          "score": 61
        },
        {
          "time": "10:06",
          "score": 61
        },
        {
          "time": "10:06",
          "score": 61
        },
        {
          "time": "10:08",
          "score": 61
        },
        {
          "time": "10:13",
          "score": 59
        }
      ],
      "observeUrl": "https://news.google.com/search?q=%E8%B8%8A%E3%81%A3%E3%81%A6%E3%81%BF%E3%81%9F%20TikTok&hl=ja&gl=JP&ceid=JP%3Aja"
    },
    {
      "id": "b1591138e1ea",
      "keyword": "花火イベント",
      "watchlist": "seasonal",
      "watchlistLabel": "季節・イベント",
      "rank": 26,
      "previousRank": 26,
      "rankChange": 0,
      "score": 59,
      "previousScore": 61,
      "scoreChange": -2,
      "yesterdayScore": null,
      "yesterdayChange": null,
      "direction": "flat",
      "trendStatus": "flat",
      "appearCount": 9,
      "signalType": "configured_rss",
      "evidenceCount": 20,
      "previousEvidenceCount": 20,
      "evidenceChange": 0,
      "capturedAt": "2026-06-29T10:13:00+09:00",
      "series": [
        {
          "time": "09:51",
          "score": 66
        },
        {
          "time": "09:53",
          "score": 60
        },
        {
          "time": "10:02",
          "score": 100
        },
        {
          "time": "10:03",
          "score": 61
        },
        {
          "time": "10:08",
          "score": 61
        },
        {
          "time": "10:13",
          "score": 59
        }
      ],
      "observeUrl": "https://news.google.com/search?q=%E8%8A%B1%E7%81%AB%20%E3%82%A4%E3%83%99%E3%83%B3%E3%83%88%20%E4%BA%BA%E6%B0%97&hl=ja&gl=JP&ceid=JP%3Aja"
    },
    {
      "id": "a450a56b7894",
      "keyword": "屋久島旅行",
      "watchlist": "local_leisure",
      "watchlistLabel": "地域・レジャー",
      "rank": 26,
      "previousRank": 26,
      "rankChange": 0,
      "score": 59,
      "previousScore": 61,
      "scoreChange": -2,
      "yesterdayScore": null,
      "yesterdayChange": null,
      "direction": "flat",
      "trendStatus": "flat",
      "appearCount": 14,
      "signalType": "configured_rss",
      "evidenceCount": 20,
      "previousEvidenceCount": 20,
      "evidenceChange": 0,
      "capturedAt": "2026-06-29T10:13:00+09:00",
      "series": [
        {
          "time": "10:03",
          "score": 61
        },
        {
          "time": "10:04",
          "score": 61
        },
        {
          "time": "10:06",
          "score": 61
        },
        {
          "time": "10:06",
          "score": 61
        },
        {
          "time": "10:08",
          "score": 61
        },
        {
          "time": "10:13",
          "score": 59
        }
      ],
      "observeUrl": "https://news.google.com/search?q=%E5%B1%8B%E4%B9%85%E5%B3%B6%20%E6%97%85%E8%A1%8C%20%E4%BA%BA%E6%B0%97&hl=ja&gl=JP&ceid=JP%3Aja"
    },
    {
      "id": "88448d216ba2",
      "keyword": "奄美旅行",
      "watchlist": "local_leisure",
      "watchlistLabel": "地域・レジャー",
      "rank": 26,
      "previousRank": 26,
      "rankChange": 0,
      "score": 59,
      "previousScore": 61,
      "scoreChange": -2,
      "yesterdayScore": null,
      "yesterdayChange": null,
      "direction": "flat",
      "trendStatus": "flat",
      "appearCount": 14,
      "signalType": "configured_rss",
      "evidenceCount": 20,
      "previousEvidenceCount": 20,
      "evidenceChange": 0,
      "capturedAt": "2026-06-29T10:13:00+09:00",
      "series": [
        {
          "time": "10:03",
          "score": 61
        },
        {
          "time": "10:04",
          "score": 61
        },
        {
          "time": "10:06",
          "score": 61
        },
        {
          "time": "10:06",
          "score": 61
        },
        {
          "time": "10:08",
          "score": 61
        },
        {
          "time": "10:13",
          "score": 59
        }
      ],
      "observeUrl": "https://news.google.com/search?q=%E5%A5%84%E7%BE%8E%20%E6%97%85%E8%A1%8C%20%E4%BA%BA%E6%B0%97&hl=ja&gl=JP&ceid=JP%3Aja"
    },
    {
      "id": "878be7cc6d85",
      "keyword": "夏休み旅行",
      "watchlist": "seasonal",
      "watchlistLabel": "季節・イベント",
      "rank": 18,
      "previousRank": 18,
      "rankChange": 0,
      "score": 58,
      "previousScore": 60,
      "scoreChange": -2,
      "yesterdayScore": null,
      "yesterdayChange": null,
      "direction": "flat",
      "trendStatus": "flat",
      "appearCount": 14,
      "signalType": "configured_rss",
      "evidenceCount": 5,
      "previousEvidenceCount": 5,
      "evidenceChange": 0,
      "capturedAt": "2026-06-29T10:13:00+09:00",
      "series": [
        {
          "time": "10:03",
          "score": 60
        },
        {
          "time": "10:04",
          "score": 60
        },
        {
          "time": "10:06",
          "score": 60
        },
        {
          "time": "10:06",
          "score": 60
        },
        {
          "time": "10:08",
          "score": 60
        },
        {
          "time": "10:13",
          "score": 58
        }
      ],
      "observeUrl": "https://news.google.com/search?q=%E5%A4%8F%E4%BC%91%E3%81%BF%20%E6%97%85%E8%A1%8C%20%E4%BA%BA%E6%B0%97&hl=ja&gl=JP&ceid=JP%3Aja"
    },
    {
      "id": "f769cd7c33e6",
      "keyword": "懐かしいネタ",
      "watchlist": "light_topic",
      "watchlistLabel": "軽い話題",
      "rank": 26,
      "previousRank": 26,
      "rankChange": 0,
      "score": 57,
      "previousScore": 59,
      "scoreChange": -2,
      "yesterdayScore": null,
      "yesterdayChange": null,
      "direction": "flat",
      "trendStatus": "flat",
      "appearCount": 14,
      "signalType": "configured_rss",
      "evidenceCount": 18,
      "previousEvidenceCount": 18,
      "evidenceChange": 0,
      "capturedAt": "2026-06-29T10:13:00+09:00",
      "series": [
        {
          "time": "10:03",
          "score": 59
        },
        {
          "time": "10:04",
          "score": 59
        },
        {
          "time": "10:06",
          "score": 59
        },
        {
          "time": "10:06",
          "score": 59
        },
        {
          "time": "10:08",
          "score": 59
        },
        {
          "time": "10:13",
          "score": 57
        }
      ],
      "observeUrl": "https://news.google.com/search?q=%E6%87%90%E3%81%8B%E3%81%97%E3%81%84%20%E3%83%8D%E3%82%BF%20SNS&hl=ja&gl=JP&ceid=JP%3Aja"
    },
    {
      "id": "7f50d163e019",
      "keyword": "かわいい投稿",
      "watchlist": "light_topic",
      "watchlistLabel": "軽い話題",
      "rank": 26,
      "previousRank": 26,
      "rankChange": 0,
      "score": 57,
      "previousScore": 59,
      "scoreChange": -2,
      "yesterdayScore": null,
      "yesterdayChange": null,
      "direction": "flat",
      "trendStatus": "flat",
      "appearCount": 14,
      "signalType": "configured_rss",
      "evidenceCount": 20,
      "previousEvidenceCount": 20,
      "evidenceChange": 0,
      "capturedAt": "2026-06-29T10:13:00+09:00",
      "series": [
        {
          "time": "10:03",
          "score": 59
        },
        {
          "time": "10:04",
          "score": 59
        },
        {
          "time": "10:06",
          "score": 59
        },
        {
          "time": "10:06",
          "score": 59
        },
        {
          "time": "10:08",
          "score": 59
        },
        {
          "time": "10:13",
          "score": 57
        }
      ],
      "observeUrl": "https://news.google.com/search?q=%E3%81%8B%E3%82%8F%E3%81%84%E3%81%84%20%E6%8A%95%E7%A8%BF%20SNS&hl=ja&gl=JP&ceid=JP%3Aja"
    },
    {
      "id": "df69d5eb7c4b",
      "keyword": "あほぽてチャレンジ",
      "watchlist": "sns_platform",
      "watchlistLabel": "SNSトレンド",
      "rank": 18,
      "previousRank": 18,
      "rankChange": 0,
      "score": 56,
      "previousScore": 60,
      "scoreChange": -4,
      "yesterdayScore": null,
      "yesterdayChange": null,
      "direction": "flat",
      "trendStatus": "flat",
      "appearCount": 11,
      "signalType": "discovered_phrase",
      "evidenceCount": 2,
      "previousEvidenceCount": 2,
      "evidenceChange": 0,
      "capturedAt": "2026-06-29T10:13:00+09:00",
      "series": [
        {
          "time": "10:03",
          "score": 65
        },
        {
          "time": "10:04",
          "score": 65
        },
        {
          "time": "10:06",
          "score": 42
        },
        {
          "time": "10:06",
          "score": 60
        },
        {
          "time": "10:08",
          "score": 60
        },
        {
          "time": "10:13",
          "score": 56
        }
      ],
      "observeUrl": "https://news.google.com/search?q=%E3%81%82%E3%81%BB%E3%81%BD%E3%81%A6%E3%83%81%E3%83%A3%E3%83%AC%E3%83%B3%E3%82%B8&hl=ja&gl=JP&ceid=JP%3Aja"
    },
    {
      "id": "dee05e77e772",
      "keyword": "薬剤師あるある",
      "watchlist": "sns_platform",
      "watchlistLabel": "SNSトレンド",
      "rank": 18,
      "previousRank": 18,
      "rankChange": 0,
      "score": 55,
      "previousScore": 41,
      "scoreChange": 14,
      "yesterdayScore": null,
      "yesterdayChange": null,
      "direction": "up",
      "trendStatus": "flat",
      "appearCount": 11,
      "signalType": "discovered_phrase",
      "evidenceCount": 2,
      "previousEvidenceCount": 2,
      "evidenceChange": 0,
      "capturedAt": "2026-06-29T10:13:00+09:00",
      "series": [
        {
          "time": "10:03",
          "score": 65
        },
        {
          "time": "10:04",
          "score": 65
        },
        {
          "time": "10:06",
          "score": 65
        },
        {
          "time": "10:06",
          "score": 65
        },
        {
          "time": "10:08",
          "score": 41
        },
        {
          "time": "10:13",
          "score": 55
        }
      ],
      "observeUrl": "https://news.google.com/search?q=%E8%96%AC%E5%89%A4%E5%B8%AB%E3%81%82%E3%82%8B%E3%81%82%E3%82%8B&hl=ja&gl=JP&ceid=JP%3Aja"
    },
    {
      "id": "06e4c1e1aaa7",
      "keyword": "釣り人あるある",
      "watchlist": "format",
      "watchlistLabel": "投稿フォーマット",
      "rank": 18,
      "previousRank": 18,
      "rankChange": 0,
      "score": 55,
      "previousScore": 59,
      "scoreChange": -4,
      "yesterdayScore": null,
      "yesterdayChange": null,
      "direction": "flat",
      "trendStatus": "flat",
      "appearCount": 10,
      "signalType": "discovered_phrase",
      "evidenceCount": 2,
      "previousEvidenceCount": 2,
      "evidenceChange": 0,
      "capturedAt": "2026-06-29T10:13:00+09:00",
      "series": [
        {
          "time": "10:03",
          "score": 59
        },
        {
          "time": "10:04",
          "score": 59
        },
        {
          "time": "10:06",
          "score": 59
        },
        {
          "time": "10:06",
          "score": 59
        },
        {
          "time": "10:08",
          "score": 59
        },
        {
          "time": "10:13",
          "score": 55
        }
      ],
      "observeUrl": "https://news.google.com/search?q=%E9%87%A3%E3%82%8A%E4%BA%BA%E3%81%82%E3%82%8B%E3%81%82%E3%82%8B&hl=ja&gl=JP&ceid=JP%3Aja"
    },
    {
      "id": "f74038d79bf5",
      "keyword": "自虐ネタ",
      "watchlist": "sns_platform",
      "watchlistLabel": "SNSトレンド",
      "rank": 21,
      "previousRank": 21,
      "rankChange": 0,
      "score": 48,
      "previousScore": 52,
      "scoreChange": -4,
      "yesterdayScore": null,
      "yesterdayChange": null,
      "direction": "flat",
      "trendStatus": "flat",
      "appearCount": 8,
      "signalType": "discovered_phrase",
      "evidenceCount": 1,
      "previousEvidenceCount": 1,
      "evidenceChange": 0,
      "capturedAt": "2026-06-29T10:13:00+09:00",
      "series": [
        {
          "time": "10:03",
          "score": 47
        },
        {
          "time": "10:04",
          "score": 52
        },
        {
          "time": "10:06",
          "score": 52
        },
        {
          "time": "10:06",
          "score": 52
        },
        {
          "time": "10:08",
          "score": 52
        },
        {
          "time": "10:13",
          "score": 48
        }
      ],
      "observeUrl": "https://news.google.com/search?q=%E8%87%AA%E8%99%90%E3%83%8D%E3%82%BF&hl=ja&gl=JP&ceid=JP%3Aja"
    },
    {
      "id": "27c0e4bef539",
      "keyword": "派生ネタ",
      "watchlist": "sns_platform",
      "watchlistLabel": "SNSトレンド",
      "rank": 21,
      "previousRank": 21,
      "rankChange": 0,
      "score": 48,
      "previousScore": 52,
      "scoreChange": -4,
      "yesterdayScore": null,
      "yesterdayChange": null,
      "direction": "flat",
      "trendStatus": "flat",
      "appearCount": 5,
      "signalType": "discovered_phrase",
      "evidenceCount": 1,
      "previousEvidenceCount": 1,
      "evidenceChange": 0,
      "capturedAt": "2026-06-29T10:13:00+09:00",
      "series": [
        {
          "time": "09:55",
          "score": 73
        },
        {
          "time": "10:06",
          "score": 42
        },
        {
          "time": "10:06",
          "score": 47
        },
        {
          "time": "10:08",
          "score": 52
        },
        {
          "time": "10:13",
          "score": 48
        }
      ],
      "observeUrl": "https://news.google.com/search?q=%E6%B4%BE%E7%94%9F%E3%83%8D%E3%82%BF&hl=ja&gl=JP&ceid=JP%3Aja"
    },
    {
      "id": "1748d88aed4c",
      "keyword": "センス抜群なSNSネタ",
      "watchlist": "sns_platform",
      "watchlistLabel": "SNSトレンド",
      "rank": 21,
      "previousRank": 21,
      "rankChange": 0,
      "score": 48,
      "previousScore": 47,
      "scoreChange": 1,
      "yesterdayScore": null,
      "yesterdayChange": null,
      "direction": "flat",
      "trendStatus": "flat",
      "appearCount": 4,
      "signalType": "discovered_phrase",
      "evidenceCount": 1,
      "previousEvidenceCount": 1,
      "evidenceChange": 0,
      "capturedAt": "2026-06-29T10:13:00+09:00",
      "series": [
        {
          "time": "10:06",
          "score": 37
        },
        {
          "time": "10:06",
          "score": 42
        },
        {
          "time": "10:08",
          "score": 47
        },
        {
          "time": "10:13",
          "score": 48
        }
      ],
      "observeUrl": "https://news.google.com/search?q=%E3%82%BB%E3%83%B3%E3%82%B9%E6%8A%9C%E7%BE%A4%E3%81%AASNS%E3%83%8D%E3%82%BF&hl=ja&gl=JP&ceid=JP%3Aja"
    },
    {
      "id": "1da54295abe2",
      "keyword": "SNSで話題の面白ネタ",
      "watchlist": "sns_platform",
      "watchlistLabel": "SNSトレンド",
      "rank": 21,
      "previousRank": 21,
      "rankChange": 0,
      "score": 48,
      "previousScore": 47,
      "scoreChange": 1,
      "yesterdayScore": null,
      "yesterdayChange": null,
      "direction": "flat",
      "trendStatus": "flat",
      "appearCount": 4,
      "signalType": "discovered_phrase",
      "evidenceCount": 1,
      "previousEvidenceCount": 1,
      "evidenceChange": 0,
      "capturedAt": "2026-06-29T10:13:00+09:00",
      "series": [
        {
          "time": "10:06",
          "score": 37
        },
        {
          "time": "10:06",
          "score": 42
        },
        {
          "time": "10:08",
          "score": 47
        },
        {
          "time": "10:13",
          "score": 48
        }
      ],
      "observeUrl": "https://news.google.com/search?q=SNS%E3%81%A7%E8%A9%B1%E9%A1%8C%E3%81%AE%E9%9D%A2%E7%99%BD%E3%83%8D%E3%82%BF&hl=ja&gl=JP&ceid=JP%3Aja"
    },
    {
      "id": "1fe922de1ffb",
      "keyword": "SNSで話題の自虐ミーム",
      "watchlist": "sns_platform",
      "watchlistLabel": "SNSトレンド",
      "rank": 21,
      "previousRank": 21,
      "rankChange": 0,
      "score": 48,
      "previousScore": 47,
      "scoreChange": 1,
      "yesterdayScore": null,
      "yesterdayChange": null,
      "direction": "flat",
      "trendStatus": "flat",
      "appearCount": 4,
      "signalType": "discovered_phrase",
      "evidenceCount": 1,
      "previousEvidenceCount": 1,
      "evidenceChange": 0,
      "capturedAt": "2026-06-29T10:13:00+09:00",
      "series": [
        {
          "time": "10:06",
          "score": 37
        },
        {
          "time": "10:06",
          "score": 42
        },
        {
          "time": "10:08",
          "score": 47
        },
        {
          "time": "10:13",
          "score": 48
        }
      ],
      "observeUrl": "https://news.google.com/search?q=SNS%E3%81%A7%E8%A9%B1%E9%A1%8C%E3%81%AE%E8%87%AA%E8%99%90%E3%83%9F%E3%83%BC%E3%83%A0&hl=ja&gl=JP&ceid=JP%3Aja"
    },
    {
      "id": "2683f07e44f5",
      "keyword": "猫ミームダンス",
      "watchlist": "sns_platform",
      "watchlistLabel": "SNSトレンド",
      "rank": 21,
      "previousRank": 21,
      "rankChange": 0,
      "score": 48,
      "previousScore": 47,
      "scoreChange": 1,
      "yesterdayScore": null,
      "yesterdayChange": null,
      "direction": "flat",
      "trendStatus": "flat",
      "appearCount": 4,
      "signalType": "discovered_phrase",
      "evidenceCount": 1,
      "previousEvidenceCount": 1,
      "evidenceChange": 0,
      "capturedAt": "2026-06-29T10:13:00+09:00",
      "series": [
        {
          "time": "10:06",
          "score": 37
        },
        {
          "time": "10:06",
          "score": 42
        },
        {
          "time": "10:08",
          "score": 47
        },
        {
          "time": "10:13",
          "score": 48
        }
      ],
      "observeUrl": "https://news.google.com/search?q=%E7%8C%AB%E3%83%9F%E3%83%BC%E3%83%A0%E3%83%80%E3%83%B3%E3%82%B9&hl=ja&gl=JP&ceid=JP%3Aja"
    },
    {
      "id": "c6f831942f81",
      "keyword": "オタク構文",
      "watchlist": "sns_platform",
      "watchlistLabel": "SNSトレンド",
      "rank": 21,
      "previousRank": 21,
      "rankChange": 0,
      "score": 48,
      "previousScore": 47,
      "scoreChange": 1,
      "yesterdayScore": null,
      "yesterdayChange": null,
      "direction": "flat",
      "trendStatus": "flat",
      "appearCount": 4,
      "signalType": "discovered_phrase",
      "evidenceCount": 1,
      "previousEvidenceCount": 1,
      "evidenceChange": 0,
      "capturedAt": "2026-06-29T10:13:00+09:00",
      "series": [
        {
          "time": "10:06",
          "score": 37
        },
        {
          "time": "10:06",
          "score": 42
        },
        {
          "time": "10:08",
          "score": 47
        },
        {
          "time": "10:13",
          "score": 48
        }
      ],
      "observeUrl": "https://news.google.com/search?q=%E3%82%AA%E3%82%BF%E3%82%AF%E6%A7%8B%E6%96%87&hl=ja&gl=JP&ceid=JP%3Aja"
    },
    {
      "id": "656cec4030db",
      "keyword": "韓流あるある",
      "watchlist": "sns_platform",
      "watchlistLabel": "SNSトレンド",
      "rank": 21,
      "previousRank": 21,
      "rankChange": 0,
      "score": 48,
      "previousScore": 47,
      "scoreChange": 1,
      "yesterdayScore": null,
      "yesterdayChange": null,
      "direction": "flat",
      "trendStatus": "flat",
      "appearCount": 4,
      "signalType": "discovered_phrase",
      "evidenceCount": 1,
      "previousEvidenceCount": 1,
      "evidenceChange": 0,
      "capturedAt": "2026-06-29T10:13:00+09:00",
      "series": [
        {
          "time": "10:06",
          "score": 37
        },
        {
          "time": "10:06",
          "score": 42
        },
        {
          "time": "10:08",
          "score": 47
        },
        {
          "time": "10:13",
          "score": 48
        }
      ],
      "observeUrl": "https://news.google.com/search?q=%E9%9F%93%E6%B5%81%E3%81%82%E3%82%8B%E3%81%82%E3%82%8B&hl=ja&gl=JP&ceid=JP%3Aja"
    },
    {
      "id": "f421b9838849",
      "keyword": "くださいませチャレンジ",
      "watchlist": "sns_platform",
      "watchlistLabel": "SNSトレンド",
      "rank": 21,
      "previousRank": 21,
      "rankChange": 0,
      "score": 48,
      "previousScore": 52,
      "scoreChange": -4,
      "yesterdayScore": null,
      "yesterdayChange": null,
      "direction": "flat",
      "trendStatus": "flat",
      "appearCount": 11,
      "signalType": "discovered_phrase",
      "evidenceCount": 1,
      "previousEvidenceCount": 1,
      "evidenceChange": 0,
      "capturedAt": "2026-06-29T10:13:00+09:00",
      "series": [
        {
          "time": "10:03",
          "score": 60
        },
        {
          "time": "10:04",
          "score": 60
        },
        {
          "time": "10:06",
          "score": 34
        },
        {
          "time": "10:06",
          "score": 52
        },
        {
          "time": "10:08",
          "score": 52
        },
        {
          "time": "10:13",
          "score": 48
        }
      ],
      "observeUrl": "https://news.google.com/search?q=%E3%81%8F%E3%81%A0%E3%81%95%E3%81%84%E3%81%BE%E3%81%9B%E3%83%81%E3%83%A3%E3%83%AC%E3%83%B3%E3%82%B8&hl=ja&gl=JP&ceid=JP%3Aja"
    },
    {
      "id": "c3f2e265787d",
      "keyword": "握手ミーム",
      "watchlist": "sns_platform",
      "watchlistLabel": "SNSトレンド",
      "rank": 21,
      "previousRank": 21,
      "rankChange": 0,
      "score": 48,
      "previousScore": 52,
      "scoreChange": -4,
      "yesterdayScore": null,
      "yesterdayChange": null,
      "direction": "flat",
      "trendStatus": "flat",
      "appearCount": 11,
      "signalType": "discovered_phrase",
      "evidenceCount": 1,
      "previousEvidenceCount": 1,
      "evidenceChange": 0,
      "capturedAt": "2026-06-29T10:13:00+09:00",
      "series": [
        {
          "time": "10:03",
          "score": 60
        },
        {
          "time": "10:04",
          "score": 60
        },
        {
          "time": "10:06",
          "score": 34
        },
        {
          "time": "10:06",
          "score": 52
        },
        {
          "time": "10:08",
          "score": 52
        },
        {
          "time": "10:13",
          "score": 48
        }
      ],
      "observeUrl": "https://news.google.com/search?q=%E6%8F%A1%E6%89%8B%E3%83%9F%E3%83%BC%E3%83%A0&hl=ja&gl=JP&ceid=JP%3Aja"
    },
    {
      "id": "69641a801e0c",
      "keyword": "芸能界でチャレンジ",
      "watchlist": "sns_platform",
      "watchlistLabel": "SNSトレンド",
      "rank": 21,
      "previousRank": 21,
      "rankChange": 0,
      "score": 48,
      "previousScore": 47,
      "scoreChange": 1,
      "yesterdayScore": null,
      "yesterdayChange": null,
      "direction": "flat",
      "trendStatus": "flat",
      "appearCount": 4,
      "signalType": "discovered_phrase",
      "evidenceCount": 1,
      "previousEvidenceCount": 1,
      "evidenceChange": 0,
      "capturedAt": "2026-06-29T10:13:00+09:00",
      "series": [
        {
          "time": "10:06",
          "score": 37
        },
        {
          "time": "10:06",
          "score": 42
        },
        {
          "time": "10:08",
          "score": 47
        },
        {
          "time": "10:13",
          "score": 48
        }
      ],
      "observeUrl": "https://news.google.com/search?q=%E8%8A%B8%E8%83%BD%E7%95%8C%E3%81%A7%E3%83%81%E3%83%A3%E3%83%AC%E3%83%B3%E3%82%B8&hl=ja&gl=JP&ceid=JP%3Aja"
    },
    {
      "id": "0abaa57ece7c",
      "keyword": "30秒で汗をかくTikTokチャレンジ",
      "watchlist": "sns_platform",
      "watchlistLabel": "SNSトレンド",
      "rank": 21,
      "previousRank": 21,
      "rankChange": 0,
      "score": 48,
      "previousScore": 47,
      "scoreChange": 1,
      "yesterdayScore": null,
      "yesterdayChange": null,
      "direction": "flat",
      "trendStatus": "flat",
      "appearCount": 4,
      "signalType": "discovered_phrase",
      "evidenceCount": 1,
      "previousEvidenceCount": 1,
      "evidenceChange": 0,
      "capturedAt": "2026-06-29T10:13:00+09:00",
      "series": [
        {
          "time": "10:06",
          "score": 37
        },
        {
          "time": "10:06",
          "score": 42
        },
        {
          "time": "10:08",
          "score": 47
        },
        {
          "time": "10:13",
          "score": 48
        }
      ],
      "observeUrl": "https://news.google.com/search?q=30%E7%A7%92%E3%81%A7%E6%B1%97%E3%82%92%E3%81%8B%E3%81%8FTikTok%E3%83%81%E3%83%A3%E3%83%AC%E3%83%B3%E3%82%B8&hl=ja&gl=JP&ceid=JP%3Aja"
    },
    {
      "id": "9b90efe6413b",
      "keyword": "GOODDAY",
      "watchlist": "sns_platform",
      "watchlistLabel": "SNSトレンド",
      "rank": 21,
      "previousRank": 21,
      "rankChange": 0,
      "score": 48,
      "previousScore": 52,
      "scoreChange": -4,
      "yesterdayScore": null,
      "yesterdayChange": null,
      "direction": "flat",
      "trendStatus": "flat",
      "appearCount": 11,
      "signalType": "discovered_phrase",
      "evidenceCount": 1,
      "previousEvidenceCount": 1,
      "evidenceChange": 0,
      "capturedAt": "2026-06-29T10:13:00+09:00",
      "series": [
        {
          "time": "10:03",
          "score": 60
        },
        {
          "time": "10:04",
          "score": 60
        },
        {
          "time": "10:06",
          "score": 34
        },
        {
          "time": "10:06",
          "score": 52
        },
        {
          "time": "10:08",
          "score": 52
        },
        {
          "time": "10:13",
          "score": 48
        }
      ],
      "observeUrl": "https://news.google.com/search?q=GOODDAY&hl=ja&gl=JP&ceid=JP%3Aja"
    },
    {
      "id": "2b64d15472d5",
      "keyword": "GOODDAY動画を楽しめる",
      "watchlist": "sns_platform",
      "watchlistLabel": "SNSトレンド",
      "rank": 21,
      "previousRank": 21,
      "rankChange": 0,
      "score": 48,
      "previousScore": 47,
      "scoreChange": 1,
      "yesterdayScore": null,
      "yesterdayChange": null,
      "direction": "flat",
      "trendStatus": "flat",
      "appearCount": 4,
      "signalType": "discovered_phrase",
      "evidenceCount": 1,
      "previousEvidenceCount": 1,
      "evidenceChange": 0,
      "capturedAt": "2026-06-29T10:13:00+09:00",
      "series": [
        {
          "time": "10:06",
          "score": 37
        },
        {
          "time": "10:06",
          "score": 42
        },
        {
          "time": "10:08",
          "score": 47
        },
        {
          "time": "10:13",
          "score": 48
        }
      ],
      "observeUrl": "https://news.google.com/search?q=GOODDAY%E5%8B%95%E7%94%BB%E3%82%92%E6%A5%BD%E3%81%97%E3%82%81%E3%82%8B&hl=ja&gl=JP&ceid=JP%3Aja"
    },
    {
      "id": "48f2967d63fb",
      "keyword": "ナルトダンス",
      "watchlist": "sns_platform",
      "watchlistLabel": "SNSトレンド",
      "rank": 21,
      "previousRank": 21,
      "rankChange": 0,
      "score": 48,
      "previousScore": 52,
      "scoreChange": -4,
      "yesterdayScore": null,
      "yesterdayChange": null,
      "direction": "flat",
      "trendStatus": "flat",
      "appearCount": 11,
      "signalType": "discovered_phrase",
      "evidenceCount": 1,
      "previousEvidenceCount": 1,
      "evidenceChange": 0,
      "capturedAt": "2026-06-29T10:13:00+09:00",
      "series": [
        {
          "time": "10:03",
          "score": 60
        },
        {
          "time": "10:04",
          "score": 60
        },
        {
          "time": "10:06",
          "score": 34
        },
        {
          "time": "10:06",
          "score": 52
        },
        {
          "time": "10:08",
          "score": 52
        },
        {
          "time": "10:13",
          "score": 48
        }
      ],
      "observeUrl": "https://news.google.com/search?q=%E3%83%8A%E3%83%AB%E3%83%88%E3%83%80%E3%83%B3%E3%82%B9&hl=ja&gl=JP&ceid=JP%3Aja"
    },
    {
      "id": "1072632ec9fb",
      "keyword": "Shop耐久配信チャレンジ",
      "watchlist": "sns_platform",
      "watchlistLabel": "SNSトレンド",
      "rank": 21,
      "previousRank": 21,
      "rankChange": 0,
      "score": 48,
      "previousScore": 47,
      "scoreChange": 1,
      "yesterdayScore": null,
      "yesterdayChange": null,
      "direction": "flat",
      "trendStatus": "flat",
      "appearCount": 4,
      "signalType": "discovered_phrase",
      "evidenceCount": 1,
      "previousEvidenceCount": 1,
      "evidenceChange": 0,
      "capturedAt": "2026-06-29T10:13:00+09:00",
      "series": [
        {
          "time": "10:06",
          "score": 37
        },
        {
          "time": "10:06",
          "score": 42
        },
        {
          "time": "10:08",
          "score": 47
        },
        {
          "time": "10:13",
          "score": 48
        }
      ],
      "observeUrl": "https://news.google.com/search?q=Shop%E8%80%90%E4%B9%85%E9%85%8D%E4%BF%A1%E3%83%81%E3%83%A3%E3%83%AC%E3%83%B3%E3%82%B8&hl=ja&gl=JP&ceid=JP%3Aja"
    },
    {
      "id": "6ffb9eda97ae",
      "keyword": "おじさん構文が元ネタ",
      "watchlist": "sns_platform",
      "watchlistLabel": "SNSトレンド",
      "rank": 21,
      "previousRank": 21,
      "rankChange": 0,
      "score": 48,
      "previousScore": 47,
      "scoreChange": 1,
      "yesterdayScore": null,
      "yesterdayChange": null,
      "direction": "flat",
      "trendStatus": "flat",
      "appearCount": 4,
      "signalType": "discovered_phrase",
      "evidenceCount": 1,
      "previousEvidenceCount": 1,
      "evidenceChange": 0,
      "capturedAt": "2026-06-29T10:13:00+09:00",
      "series": [
        {
          "time": "10:06",
          "score": 37
        },
        {
          "time": "10:06",
          "score": 42
        },
        {
          "time": "10:08",
          "score": 47
        },
        {
          "time": "10:13",
          "score": 48
        }
      ],
      "observeUrl": "https://news.google.com/search?q=%E3%81%8A%E3%81%98%E3%81%95%E3%82%93%E6%A7%8B%E6%96%87%E3%81%8C%E5%85%83%E3%83%8D%E3%82%BF&hl=ja&gl=JP&ceid=JP%3Aja"
    },
    {
      "id": "eadd8b8c3955",
      "keyword": "富士初登山チャレンジ",
      "watchlist": "sns_platform",
      "watchlistLabel": "SNSトレンド",
      "rank": 21,
      "previousRank": 21,
      "rankChange": 0,
      "score": 48,
      "previousScore": 47,
      "scoreChange": 1,
      "yesterdayScore": null,
      "yesterdayChange": null,
      "direction": "flat",
      "trendStatus": "flat",
      "appearCount": 4,
      "signalType": "discovered_phrase",
      "evidenceCount": 1,
      "previousEvidenceCount": 1,
      "evidenceChange": 0,
      "capturedAt": "2026-06-29T10:13:00+09:00",
      "series": [
        {
          "time": "10:06",
          "score": 37
        },
        {
          "time": "10:06",
          "score": 42
        },
        {
          "time": "10:08",
          "score": 47
        },
        {
          "time": "10:13",
          "score": 48
        }
      ],
      "observeUrl": "https://news.google.com/search?q=%E5%AF%8C%E5%A3%AB%E5%88%9D%E7%99%BB%E5%B1%B1%E3%83%81%E3%83%A3%E3%83%AC%E3%83%B3%E3%82%B8&hl=ja&gl=JP&ceid=JP%3Aja"
    },
    {
      "id": "642eb7eba599",
      "keyword": "TikTokで歌ってみたチャレンジ",
      "watchlist": "sns_platform",
      "watchlistLabel": "SNSトレンド",
      "rank": 21,
      "previousRank": 21,
      "rankChange": 0,
      "score": 48,
      "previousScore": 47,
      "scoreChange": 1,
      "yesterdayScore": null,
      "yesterdayChange": null,
      "direction": "flat",
      "trendStatus": "flat",
      "appearCount": 4,
      "signalType": "discovered_phrase",
      "evidenceCount": 1,
      "previousEvidenceCount": 1,
      "evidenceChange": 0,
      "capturedAt": "2026-06-29T10:13:00+09:00",
      "series": [
        {
          "time": "10:06",
          "score": 37
        },
        {
          "time": "10:06",
          "score": 42
        },
        {
          "time": "10:08",
          "score": 47
        },
        {
          "time": "10:13",
          "score": 48
        }
      ],
      "observeUrl": "https://news.google.com/search?q=TikTok%E3%81%A7%E6%AD%8C%E3%81%A3%E3%81%A6%E3%81%BF%E3%81%9F%E3%83%81%E3%83%A3%E3%83%AC%E3%83%B3%E3%82%B8&hl=ja&gl=JP&ceid=JP%3Aja"
    },
    {
      "id": "1b1cb41fb2c8",
      "keyword": "ハッシュタグチャレンジ",
      "watchlist": "sns_platform",
      "watchlistLabel": "SNSトレンド",
      "rank": 21,
      "previousRank": 21,
      "rankChange": 0,
      "score": 48,
      "previousScore": 47,
      "scoreChange": 1,
      "yesterdayScore": null,
      "yesterdayChange": null,
      "direction": "flat",
      "trendStatus": "flat",
      "appearCount": 4,
      "signalType": "discovered_phrase",
      "evidenceCount": 1,
      "previousEvidenceCount": 1,
      "evidenceChange": 0,
      "capturedAt": "2026-06-29T10:13:00+09:00",
      "series": [
        {
          "time": "10:06",
          "score": 37
        },
        {
          "time": "10:06",
          "score": 42
        },
        {
          "time": "10:08",
          "score": 47
        },
        {
          "time": "10:13",
          "score": 48
        }
      ],
      "observeUrl": "https://news.google.com/search?q=%E3%83%8F%E3%83%83%E3%82%B7%E3%83%A5%E3%82%BF%E3%82%B0%E3%83%81%E3%83%A3%E3%83%AC%E3%83%B3%E3%82%B8&hl=ja&gl=JP&ceid=JP%3Aja"
    },
    {
      "id": "920b5264141e",
      "keyword": "小林ゆあ界隈",
      "watchlist": "sns_platform",
      "watchlistLabel": "SNSトレンド",
      "rank": 21,
      "previousRank": 21,
      "rankChange": 0,
      "score": 48,
      "previousScore": 52,
      "scoreChange": -4,
      "yesterdayScore": null,
      "yesterdayChange": null,
      "direction": "flat",
      "trendStatus": "flat",
      "appearCount": 11,
      "signalType": "discovered_phrase",
      "evidenceCount": 1,
      "previousEvidenceCount": 1,
      "evidenceChange": 0,
      "capturedAt": "2026-06-29T10:13:00+09:00",
      "series": [
        {
          "time": "10:03",
          "score": 60
        },
        {
          "time": "10:04",
          "score": 60
        },
        {
          "time": "10:06",
          "score": 34
        },
        {
          "time": "10:06",
          "score": 52
        },
        {
          "time": "10:08",
          "score": 52
        },
        {
          "time": "10:13",
          "score": 48
        }
      ],
      "observeUrl": "https://news.google.com/search?q=%E5%B0%8F%E6%9E%97%E3%82%86%E3%81%82%E7%95%8C%E9%9A%88&hl=ja&gl=JP&ceid=JP%3Aja"
    },
    {
      "id": "53529c077560",
      "keyword": "洋楽や最新ダンス",
      "watchlist": "sns_platform",
      "watchlistLabel": "SNSトレンド",
      "rank": 21,
      "previousRank": 21,
      "rankChange": 0,
      "score": 48,
      "previousScore": 47,
      "scoreChange": 1,
      "yesterdayScore": null,
      "yesterdayChange": null,
      "direction": "flat",
      "trendStatus": "flat",
      "appearCount": 4,
      "signalType": "discovered_phrase",
      "evidenceCount": 1,
      "previousEvidenceCount": 1,
      "evidenceChange": 0,
      "capturedAt": "2026-06-29T10:13:00+09:00",
      "series": [
        {
          "time": "10:06",
          "score": 37
        },
        {
          "time": "10:06",
          "score": 42
        },
        {
          "time": "10:08",
          "score": 47
        },
        {
          "time": "10:13",
          "score": 48
        }
      ],
      "observeUrl": "https://news.google.com/search?q=%E6%B4%8B%E6%A5%BD%E3%82%84%E6%9C%80%E6%96%B0%E3%83%80%E3%83%B3%E3%82%B9&hl=ja&gl=JP&ceid=JP%3Aja"
    },
    {
      "id": "af94df3435ed",
      "keyword": "29からオリジナル音源",
      "watchlist": "sns_platform",
      "watchlistLabel": "SNSトレンド",
      "rank": 21,
      "previousRank": 21,
      "rankChange": 0,
      "score": 48,
      "previousScore": 47,
      "scoreChange": 1,
      "yesterdayScore": null,
      "yesterdayChange": null,
      "direction": "flat",
      "trendStatus": "flat",
      "appearCount": 4,
      "signalType": "discovered_phrase",
      "evidenceCount": 1,
      "previousEvidenceCount": 1,
      "evidenceChange": 0,
      "capturedAt": "2026-06-29T10:13:00+09:00",
      "series": [
        {
          "time": "10:06",
          "score": 37
        },
        {
          "time": "10:06",
          "score": 42
        },
        {
          "time": "10:08",
          "score": 47
        },
        {
          "time": "10:13",
          "score": 48
        }
      ],
      "observeUrl": "https://news.google.com/search?q=29%E3%81%8B%E3%82%89%E3%82%AA%E3%83%AA%E3%82%B8%E3%83%8A%E3%83%AB%E9%9F%B3%E6%BA%90&hl=ja&gl=JP&ceid=JP%3Aja"
    },
    {
      "id": "224bb73ee59d",
      "keyword": "8からオリジナル音源",
      "watchlist": "sns_platform",
      "watchlistLabel": "SNSトレンド",
      "rank": 21,
      "previousRank": 21,
      "rankChange": 0,
      "score": 48,
      "previousScore": 47,
      "scoreChange": 1,
      "yesterdayScore": null,
      "yesterdayChange": null,
      "direction": "flat",
      "trendStatus": "flat",
      "appearCount": 4,
      "signalType": "discovered_phrase",
      "evidenceCount": 1,
      "previousEvidenceCount": 1,
      "evidenceChange": 0,
      "capturedAt": "2026-06-29T10:13:00+09:00",
      "series": [
        {
          "time": "10:06",
          "score": 37
        },
        {
          "time": "10:06",
          "score": 42
        },
        {
          "time": "10:08",
          "score": 47
        },
        {
          "time": "10:13",
          "score": 48
        }
      ],
      "observeUrl": "https://news.google.com/search?q=8%E3%81%8B%E3%82%89%E3%82%AA%E3%83%AA%E3%82%B8%E3%83%8A%E3%83%AB%E9%9F%B3%E6%BA%90&hl=ja&gl=JP&ceid=JP%3Aja"
    },
    {
      "id": "564a69e4319b",
      "keyword": "寝返りチャレンジ",
      "watchlist": "sns_platform",
      "watchlistLabel": "SNSトレンド",
      "rank": 21,
      "previousRank": 21,
      "rankChange": 0,
      "score": 47,
      "previousScore": 51,
      "scoreChange": -4,
      "yesterdayScore": null,
      "yesterdayChange": null,
      "direction": "flat",
      "trendStatus": "flat",
      "appearCount": 11,
      "signalType": "discovered_phrase",
      "evidenceCount": 1,
      "previousEvidenceCount": 1,
      "evidenceChange": 0,
      "capturedAt": "2026-06-29T10:13:00+09:00",
      "series": [
        {
          "time": "10:03",
          "score": 59
        },
        {
          "time": "10:04",
          "score": 59
        },
        {
          "time": "10:06",
          "score": 33
        },
        {
          "time": "10:06",
          "score": 51
        },
        {
          "time": "10:08",
          "score": 51
        },
        {
          "time": "10:13",
          "score": 47
        }
      ],
      "observeUrl": "https://news.google.com/search?q=%E5%AF%9D%E8%BF%94%E3%82%8A%E3%83%81%E3%83%A3%E3%83%AC%E3%83%B3%E3%82%B8&hl=ja&gl=JP&ceid=JP%3Aja"
    },
    {
      "id": "369725a50873",
      "keyword": "日常あるある",
      "watchlist": "sns_platform",
      "watchlistLabel": "SNSトレンド",
      "rank": 21,
      "previousRank": 21,
      "rankChange": 0,
      "score": 47,
      "previousScore": 46,
      "scoreChange": 1,
      "yesterdayScore": null,
      "yesterdayChange": null,
      "direction": "flat",
      "trendStatus": "flat",
      "appearCount": 4,
      "signalType": "discovered_phrase",
      "evidenceCount": 1,
      "previousEvidenceCount": 1,
      "evidenceChange": 0,
      "capturedAt": "2026-06-29T10:13:00+09:00",
      "series": [
        {
          "time": "10:06",
          "score": 36
        },
        {
          "time": "10:06",
          "score": 41
        },
        {
          "time": "10:08",
          "score": 46
        },
        {
          "time": "10:13",
          "score": 47
        }
      ],
      "observeUrl": "https://news.google.com/search?q=%E6%97%A5%E5%B8%B8%E3%81%82%E3%82%8B%E3%81%82%E3%82%8B&hl=ja&gl=JP&ceid=JP%3Aja"
    },
    {
      "id": "c0a579914355",
      "keyword": "横手市の人なら理解できるあるある",
      "watchlist": "sns_platform",
      "watchlistLabel": "SNSトレンド",
      "rank": 21,
      "previousRank": 21,
      "rankChange": 0,
      "score": 47,
      "previousScore": 46,
      "scoreChange": 1,
      "yesterdayScore": null,
      "yesterdayChange": null,
      "direction": "flat",
      "trendStatus": "flat",
      "appearCount": 4,
      "signalType": "discovered_phrase",
      "evidenceCount": 1,
      "previousEvidenceCount": 1,
      "evidenceChange": 0,
      "capturedAt": "2026-06-29T10:13:00+09:00",
      "series": [
        {
          "time": "10:06",
          "score": 36
        },
        {
          "time": "10:06",
          "score": 41
        },
        {
          "time": "10:08",
          "score": 46
        },
        {
          "time": "10:13",
          "score": 47
        }
      ],
      "observeUrl": "https://news.google.com/search?q=%E6%A8%AA%E6%89%8B%E5%B8%82%E3%81%AE%E4%BA%BA%E3%81%AA%E3%82%89%E7%90%86%E8%A7%A3%E3%81%A7%E3%81%8D%E3%82%8B%E3%81%82%E3%82%8B%E3%81%82%E3%82%8B&hl=ja&gl=JP&ceid=JP%3Aja"
    },
    {
      "id": "c1410c87b540",
      "keyword": "今後も映像でさまざまなチャレンジ",
      "watchlist": "sns_platform",
      "watchlistLabel": "SNSトレンド",
      "rank": 21,
      "previousRank": 21,
      "rankChange": 0,
      "score": 47,
      "previousScore": 46,
      "scoreChange": 1,
      "yesterdayScore": null,
      "yesterdayChange": null,
      "direction": "flat",
      "trendStatus": "flat",
      "appearCount": 4,
      "signalType": "discovered_phrase",
      "evidenceCount": 1,
      "previousEvidenceCount": 1,
      "evidenceChange": 0,
      "capturedAt": "2026-06-29T10:13:00+09:00",
      "series": [
        {
          "time": "10:06",
          "score": 36
        },
        {
          "time": "10:06",
          "score": 41
        },
        {
          "time": "10:08",
          "score": 46
        },
        {
          "time": "10:13",
          "score": 47
        }
      ],
      "observeUrl": "https://news.google.com/search?q=%E4%BB%8A%E5%BE%8C%E3%82%82%E6%98%A0%E5%83%8F%E3%81%A7%E3%81%95%E3%81%BE%E3%81%96%E3%81%BE%E3%81%AA%E3%83%81%E3%83%A3%E3%83%AC%E3%83%B3%E3%82%B8&hl=ja&gl=JP&ceid=JP%3Aja"
    },
    {
      "id": "c62375e08544",
      "keyword": "父親あるある",
      "watchlist": "sns_platform",
      "watchlistLabel": "SNSトレンド",
      "rank": 21,
      "previousRank": 21,
      "rankChange": 0,
      "score": 47,
      "previousScore": 33,
      "scoreChange": 14,
      "yesterdayScore": null,
      "yesterdayChange": null,
      "direction": "up",
      "trendStatus": "flat",
      "appearCount": 9,
      "signalType": "discovered_phrase",
      "evidenceCount": 1,
      "previousEvidenceCount": 1,
      "evidenceChange": 0,
      "capturedAt": "2026-06-29T10:13:00+09:00",
      "series": [
        {
          "time": "09:55",
          "score": 82
        },
        {
          "time": "10:02",
          "score": 59
        },
        {
          "time": "10:03",
          "score": 59
        },
        {
          "time": "10:04",
          "score": 59
        },
        {
          "time": "10:08",
          "score": 33
        },
        {
          "time": "10:13",
          "score": 47
        }
      ],
      "observeUrl": "https://news.google.com/search?q=%E7%88%B6%E8%A6%AA%E3%81%82%E3%82%8B%E3%81%82%E3%82%8B&hl=ja&gl=JP&ceid=JP%3Aja"
    },
    {
      "id": "3cfd68c44e40",
      "keyword": "みんなで初心LOVE",
      "watchlist": "sns_platform",
      "watchlistLabel": "SNSトレンド",
      "rank": 21,
      "previousRank": 21,
      "rankChange": 0,
      "score": 47,
      "previousScore": 33,
      "scoreChange": 14,
      "yesterdayScore": null,
      "yesterdayChange": null,
      "direction": "up",
      "trendStatus": "flat",
      "appearCount": 8,
      "signalType": "discovered_phrase",
      "evidenceCount": 1,
      "previousEvidenceCount": 1,
      "evidenceChange": 0,
      "capturedAt": "2026-06-29T10:13:00+09:00",
      "series": [
        {
          "time": "09:55",
          "score": 77
        },
        {
          "time": "10:02",
          "score": 59
        },
        {
          "time": "10:03",
          "score": 59
        },
        {
          "time": "10:04",
          "score": 59
        },
        {
          "time": "10:08",
          "score": 33
        },
        {
          "time": "10:13",
          "score": 47
        }
      ],
      "observeUrl": "https://news.google.com/search?q=%E3%81%BF%E3%82%93%E3%81%AA%E3%81%A7%E5%88%9D%E5%BF%83LOVE&hl=ja&gl=JP&ceid=JP%3Aja"
    },
    {
      "id": "374cd72ef775",
      "keyword": "南九州イベント",
      "watchlist": "local_leisure",
      "watchlistLabel": "地域・レジャー",
      "rank": 22,
      "previousRank": 22,
      "rankChange": 0,
      "score": 45,
      "previousScore": 47,
      "scoreChange": -2,
      "yesterdayScore": null,
      "yesterdayChange": null,
      "direction": "flat",
      "trendStatus": "flat",
      "appearCount": 11,
      "signalType": "configured_rss",
      "evidenceCount": 2,
      "previousEvidenceCount": 2,
      "evidenceChange": 0,
      "capturedAt": "2026-06-29T10:13:00+09:00",
      "series": [
        {
          "time": "10:03",
          "score": 47
        },
        {
          "time": "10:04",
          "score": 47
        },
        {
          "time": "10:06",
          "score": 47
        },
        {
          "time": "10:06",
          "score": 47
        },
        {
          "time": "10:08",
          "score": 47
        },
        {
          "time": "10:13",
          "score": 45
        }
      ],
      "observeUrl": "https://news.google.com/search?q=%E5%8D%97%E4%B9%9D%E5%B7%9E%20%E3%82%A4%E3%83%99%E3%83%B3%E3%83%88%20%E8%A9%B1%E9%A1%8C&hl=ja&gl=JP&ceid=JP%3Aja"
    },
    {
      "id": "e5a34e9f691b",
      "keyword": "鹿児島観光",
      "watchlist": "local_leisure",
      "watchlistLabel": "地域・レジャー",
      "rank": 24,
      "previousRank": 24,
      "rankChange": 0,
      "score": 44,
      "previousScore": 46,
      "scoreChange": -2,
      "yesterdayScore": null,
      "yesterdayChange": null,
      "direction": "flat",
      "trendStatus": "flat",
      "appearCount": 9,
      "signalType": "configured_rss",
      "evidenceCount": 1,
      "previousEvidenceCount": 1,
      "evidenceChange": 0,
      "capturedAt": "2026-06-29T10:13:00+09:00",
      "series": [
        {
          "time": "10:03",
          "score": 46
        },
        {
          "time": "10:04",
          "score": 46
        },
        {
          "time": "10:06",
          "score": 46
        },
        {
          "time": "10:06",
          "score": 46
        },
        {
          "time": "10:08",
          "score": 46
        },
        {
          "time": "10:13",
          "score": 44
        }
      ],
      "observeUrl": "https://news.google.com/search?q=%E9%B9%BF%E5%85%90%E5%B3%B6%20%E8%A6%B3%E5%85%89%20%E4%BA%BA%E6%B0%97&hl=ja&gl=JP&ceid=JP%3Aja"
    },
    {
      "id": "c1691dcecad4",
      "keyword": "温泉旅行",
      "watchlist": "local_leisure",
      "watchlistLabel": "地域・レジャー",
      "rank": 25,
      "previousRank": 25,
      "rankChange": 0,
      "score": 43,
      "previousScore": 45,
      "scoreChange": -2,
      "yesterdayScore": null,
      "yesterdayChange": null,
      "direction": "flat",
      "trendStatus": "flat",
      "appearCount": 9,
      "signalType": "configured_rss",
      "evidenceCount": 1,
      "previousEvidenceCount": 1,
      "evidenceChange": 0,
      "capturedAt": "2026-06-29T10:13:00+09:00",
      "series": [
        {
          "time": "10:03",
          "score": 45
        },
        {
          "time": "10:04",
          "score": 45
        },
        {
          "time": "10:06",
          "score": 45
        },
        {
          "time": "10:06",
          "score": 45
        },
        {
          "time": "10:08",
          "score": 45
        },
        {
          "time": "10:13",
          "score": 43
        }
      ],
      "observeUrl": "https://news.google.com/search?q=%E6%B8%A9%E6%B3%89%20%E6%97%85%E8%A1%8C%20%E4%BA%BA%E6%B0%97&hl=ja&gl=JP&ceid=JP%3Aja"
    },
    {
      "id": "727452de81b1",
      "keyword": "お盆旅行",
      "watchlist": "seasonal",
      "watchlistLabel": "季節・イベント",
      "rank": 25,
      "previousRank": 25,
      "rankChange": 0,
      "score": 42,
      "previousScore": 44,
      "scoreChange": -2,
      "yesterdayScore": null,
      "yesterdayChange": null,
      "direction": "flat",
      "trendStatus": "flat",
      "appearCount": 8,
      "signalType": "configured_rss",
      "evidenceCount": 1,
      "previousEvidenceCount": 1,
      "evidenceChange": 0,
      "capturedAt": "2026-06-29T10:13:00+09:00",
      "series": [
        {
          "time": "09:44",
          "score": 58
        },
        {
          "time": "10:04",
          "score": 44
        },
        {
          "time": "10:06",
          "score": 44
        },
        {
          "time": "10:06",
          "score": 44
        },
        {
          "time": "10:08",
          "score": 44
        },
        {
          "time": "10:13",
          "score": 42
        }
      ],
      "observeUrl": "https://news.google.com/search?q=%E3%81%8A%E7%9B%86%20%E6%97%85%E8%A1%8C%20%E4%BA%BA%E6%B0%97&hl=ja&gl=JP&ceid=JP%3Aja"
    },
    {
      "id": "31def58e98f2",
      "keyword": "便利グッズ",
      "watchlist": "light_topic",
      "watchlistLabel": "軽い話題",
      "rank": 25,
      "previousRank": 25,
      "rankChange": 0,
      "score": 42,
      "previousScore": 44,
      "scoreChange": -2,
      "yesterdayScore": null,
      "yesterdayChange": null,
      "direction": "flat",
      "trendStatus": "flat",
      "appearCount": 8,
      "signalType": "configured_rss",
      "evidenceCount": 1,
      "previousEvidenceCount": 1,
      "evidenceChange": 0,
      "capturedAt": "2026-06-29T10:13:00+09:00",
      "series": [
        {
          "time": "09:44",
          "score": 57
        },
        {
          "time": "10:04",
          "score": 44
        },
        {
          "time": "10:06",
          "score": 44
        },
        {
          "time": "10:06",
          "score": 44
        },
        {
          "time": "10:08",
          "score": 44
        },
        {
          "time": "10:13",
          "score": 42
        }
      ],
      "observeUrl": "https://news.google.com/search?q=%E4%BE%BF%E5%88%A9%20%E3%82%B0%E3%83%83%E3%82%BA%20%E8%A9%B1%E9%A1%8C&hl=ja&gl=JP&ceid=JP%3Aja"
    }
  ]
}
